vtwirp/__init__.py
vtwirp/asgi.py
vtwirp/base.py
vtwirp/client.py
vtwirp/ctxkeys.py
vtwirp/errors.py
vtwirp/exceptions.py
vtwirp/hook.py
vtwirp/middlewares.py
vtwirp/server.py
vtwirp/hooks/__init__.py
vtwirp/hooks/client_id.py
vtwirp/hooks/logging.py
vtwirp-0.0.3.dist-info/METADATA
vtwirp-0.0.3.dist-info/WHEEL
vtwirp-0.0.3.dist-info/top_level.txt
vtwirp-0.0.3.dist-info/RECORD
